isee_club/__init__.py
isee_club/datetime_utils.py
isee_club-0.1.2.dist-info/METADATA
isee_club-0.1.2.dist-info/WHEEL
isee_club-0.1.2.dist-info/top_level.txt
isee_club-0.1.2.dist-info/RECORD
