Metadata-Version: 2.1
Name: isee_club
Version: 0.1.2
Summary: isee club is public library
Home-page: 
Author: isee
Author-email: 
Requires-Dist: pytz==2024.2
